cashy/__init__.py
cashy/cashy.py
cashy/example_usage.py
cashy-1.0.0.dist-info/licenses/LICENSE
cashy-1.0.0.dist-info/METADATA
cashy-1.0.0.dist-info/WHEEL
cashy-1.0.0.dist-info/top_level.txt
cashy-1.0.0.dist-info/RECORD
