Metadata-Version: 2.4
Name: cashy
Version: 1.0.0
Summary: A simple Live currency converter using the Frankfurter API
Home-page: https://github.com/mohsin-nasir/cashy
Author: Mohsin Nasir
Author-email: mohsinnasirdps@gmail.com
Classifier: Programming Language :: Python :: 3
Classifier: License :: OSI Approved :: MIT License
Classifier: Operating System :: OS Independent
Requires-Python: >=3.6
License-File: LICENSE
Requires-Dist: requests>=2.0.0
Dynamic: author
Dynamic: author-email
Dynamic: classifier
Dynamic: description
Dynamic: description-content-type
Dynamic: home-page
Dynamic: license-file
Dynamic: requires-dist
Dynamic: requires-python
Dynamic: summary
